LrnXPAnaToolbox/LrnXPAnaToolbox.py
LrnXPAnaToolbox/__init__.py
LrnXPAnaToolbox/__main__.py
LrnXPAnaToolbox/lib.py
LrnXPAnaToolbox/cluster_students/__init__.py
LrnXPAnaToolbox/cluster_students/cluster_students.py
LrnXPAnaToolbox/create_marks/__init__.py
LrnXPAnaToolbox/create_marks/create_marks.py
LrnXPAnaToolbox/recommander/__init__.py
LrnXPAnaToolbox/recommander/dropout.py
LrnXPAnaToolbox/recommander/final_test_recommendation.py
LrnXPAnaToolbox/recommander/recommander.py
LrnXPAnaToolbox/recommender/__init__.py
LrnXPAnaToolbox/recommender/dropout.py
LrnXPAnaToolbox/recommender/final_recommendation.py
LrnXPAnaToolbox/recommender/recommender.py
LrnXPAnaToolbox/transform_data/__init__.py
LrnXPAnaToolbox/transform_data/transform_data.py
LrnXPAnaToolbox-0.4.1.dist-info/AUTHORS.rst
LrnXPAnaToolbox-0.4.1.dist-info/LICENSE
LrnXPAnaToolbox-0.4.1.dist-info/METADATA
LrnXPAnaToolbox-0.4.1.dist-info/WHEEL
LrnXPAnaToolbox-0.4.1.dist-info/entry_points.txt
LrnXPAnaToolbox-0.4.1.dist-info/top_level.txt
LrnXPAnaToolbox-0.4.1.dist-info/RECORD
