Metadata-Version: 2.1
Name: LrnXPAnaToolbox
Version: 0.4.1
Summary: Learning Experience Analysis Toolbox contains tools to analyse learning experience data using the pandas library. This package is developped for EvidenceB leraning experience data.
Home-page: https://github.com/robachkaya/LrnXPAnaToolbox
Author: Kayané Elmayan Robach
Author-email: kaya.robach@gmail.com
License: MIT license
Keywords: LrnXPAnaToolbox
Platform: UNKNOWN
Classifier: Development Status :: 2 - Pre-Alpha
Classifier: Intended Audience :: Developers
Classifier: License :: OSI Approved :: MIT License
Classifier: Natural Language :: English
Classifier: Programming Language :: Python :: 3
Classifier: Programming Language :: Python :: 3.5
Classifier: Programming Language :: Python :: 3.6
Classifier: Programming Language :: Python :: 3.7
Classifier: Programming Language :: Python :: 3.8
Requires-Python: >=3.5
Requires-Dist: ijson
Requires-Dist: numpy
Requires-Dist: pandas
Requires-Dist: tqdm
Requires-Dist: scikit-learn
Requires-Dist: matplotlib
